README.md
setup.py
alfacoins_api_python/__init__.py
alfacoins_api_python/exceptions.py
alfacoins_api_python/gateway.py
alfacoins_api_python.egg-info/PKG-INFO
alfacoins_api_python.egg-info/SOURCES.txt
alfacoins_api_python.egg-info/dependency_links.txt
alfacoins_api_python.egg-info/requires.txt
alfacoins_api_python.egg-info/top_level.txt
tests/__init__.py
tests/helper.py
tests/test_bitsend.py
tests/test_bitsend_status.py
tests/test_create_order.py
tests/test_get_fees.py
tests/test_get_rate.py
tests/test_get_rates.py
tests/test_order_status.py
tests/test_refund.py
tests/test_request.py
tests/test_statistics.py