Metadata-Version: 2.1
Name: alfacoins-api-python
Version: 0.1.2
Summary: ALFAcoins API Python 3.6+ Library
Home-page: https://github.com/alfacoins/alfacoins-api-python
Author: Arash Fatahzade
Author-email: fatahzade@gmail.com
License: MIT
Platform: UNKNOWN
Classifier: Development Status :: 3 - Alpha
Classifier: Intended Audience :: Developers
Classifier: Intended Audience :: Customer Service
Classifier: License :: OSI Approved :: MIT License
Classifier: Operating System :: MacOS
Classifier: Operating System :: Microsoft :: Windows
Classifier: Operating System :: POSIX
Classifier: Programming Language :: Python :: 3.6
Classifier: Topic :: Software Development :: Libraries :: Python Modules
